example_package_meyerno/__init__.py
example_package_meyerno/example.py
packaging_tutorial_meyerno-1.0.0.dist-info/LICENSE
packaging_tutorial_meyerno-1.0.0.dist-info/METADATA
packaging_tutorial_meyerno-1.0.0.dist-info/WHEEL
packaging_tutorial_meyerno-1.0.0.dist-info/top_level.txt
packaging_tutorial_meyerno-1.0.0.dist-info/RECORD
