Metadata-Version: 2.1
Name: packaging_tutorial_meyerno
Version: 1.0.0
Summary: A simple Python package
Author: Nico Meyer
Author-email: nico.meyer@iis.fraunhofer.de
License: Apache License 2.0
Classifier: Programming Language :: Python :: 3
Classifier: License :: OSI Approved :: Apache Software License
Classifier: Operating System :: OS Independent
Requires-Python: ~=3.12
License-File: LICENSE
Requires-Dist: numpy ~=1.26
